StableCox/Logger.py
StableCox/StableCox.py
StableCox/__init__.py
StableCox/metrics.py
StableCox/utils.py
StableCox-0.3.dist-info/LICENSE
StableCox-0.3.dist-info/METADATA
StableCox-0.3.dist-info/WHEEL
StableCox-0.3.dist-info/top_level.txt
StableCox-0.3.dist-info/RECORD
