Metadata-Version: 2.1
Name: StableCox
Version: 0.3
Summary: The official implement of Stable Cox
Home-page: https://github.com/googlebaba/StableCox
Author: Shaohua Fan
Author-email: shaohuafan@tsinghua.edu.cn
Classifier: Programming Language :: Python :: 3
Classifier: License :: OSI Approved :: MIT License
Classifier: Operating System :: OS Independent
Requires-Python: >=3.6
License-File: LICENSE
